rag_mcp_server_lizhibing/config.py
rag_mcp_server_lizhibing/server.py
rag_mcp_server_lizhibing/service.py
rag_mcp_server_lizhibing/schemas/__init__.py
rag_mcp_server_lizhibing/schemas/rag.py
rag_mcp_server_lizhibing-0.1.10.dist-info/METADATA
rag_mcp_server_lizhibing-0.1.10.dist-info/WHEEL
rag_mcp_server_lizhibing-0.1.10.dist-info/entry_points.txt
rag_mcp_server_lizhibing-0.1.10.dist-info/top_level.txt
rag_mcp_server_lizhibing-0.1.10.dist-info/RECORD
