Metadata-Version: 2.4
Name: rag-mcp-server-lizhibing
Version: 0.1.10
Summary: RAG MCP Server for document search and retrieval
Home-page: https://github.com/yourusername/rag-mcp-server
Author: Your Name
Author-email: Your Name <your.email@example.com>
License: MIT
Project-URL: Homepage, https://github.com/yourusername/rag-mcp-server
Project-URL: Repository, https://github.com/yourusername/rag-mcp-server.git
Project-URL: Issues, https://github.com/yourusername/rag-mcp-server/issues
Keywords: mcp,rag,document-search,ai
Classifier: Development Status :: 3 - Alpha
Classifier: Intended Audience :: Developers
Classifier: License :: OSI Approved :: MIT License
Classifier: Programming Language :: Python :: 3
Classifier: Programming Language :: Python :: 3.11
Classifier: Programming Language :: Python :: 3.12
Requires-Python: >=3.11
Requires-Dist: httpx>=0.28.1
Requires-Dist: mcp[cli]>=1.13.0
Requires-Dist: fastapi>=0.104.0
Requires-Dist: uvicorn>=0.24.0
Requires-Dist: pydantic>=2.0.0
Requires-Dist: python-dotenv>=1.0.0
Dynamic: author
Dynamic: home-page
Dynamic: requires-python
